LICENSE
README.md
setup.py
stacmap/__init__.py
stacmap/explore.py
stacmap/geojson.py
stacmap/stac.py
stacmap/types.py
stacmap/utils.py
stacmap.egg-info/PKG-INFO
stacmap.egg-info/SOURCES.txt
stacmap.egg-info/dependency_links.txt
stacmap.egg-info/requires.txt
stacmap.egg-info/top_level.txt