Metadata-Version: 2.1
Name: stacmap
Version: 0.0.4
Summary: Create interactive maps of STAC items.
Home-page: https://github.com/aazuspan/stacmap
Author: Aaron Zuspan
Author-email: aazuspan@gmail.com
License: MIT
Keywords: STAC,folium,map,interactive,cloud-native-geospatial
Platform: UNKNOWN
Classifier: Development Status :: 2 - Pre-Alpha
Classifier: Intended Audience :: Science/Research
Classifier: Natural Language :: English
Classifier: Topic :: Scientific/Engineering :: GIS
Classifier: Programming Language :: Python :: 3
Classifier: Programming Language :: Python :: 3.7
Classifier: Programming Language :: Python :: 3.8
Classifier: Programming Language :: Python :: 3.9
Classifier: Programming Language :: Python :: 3.10
Classifier: Typing :: Typed
Requires-Python: >=3.7
Provides-Extra: doc
Provides-Extra: dev
Provides-Extra: test
License-File: LICENSE
